{
    "Version": "2012-10-17",
    "Statement": [
        {
            "Sid": "VisualEditor0",
            "Effect": "Allow",
            "Action": [
                "autoscaling:AttachInstances",
                "autoscaling:CreateAutoScalingGroup",
                "autoscaling:CreateLaunchConfiguration",
                "autoscaling:CreateOrUpdateTags",
                "autoscaling:DeleteAutoScalingGroup",
                "autoscaling:DeleteTags",
                "autoscaling:Describe*",
                "autoscaling:DetachInstances",
                "autoscaling:SetDesiredCapacity",
                "autoscaling:SuspendProcesses",
                "autoscaling:UpdateAutoScalingGroup",
                "elasticfilesystem:CreateAccessPoint",
                "elasticfilesystem:CreateFileSystem",
                "elasticfilesystem:CreateMountTarget",
                "elasticfilesystem:CreateTags",
                "elasticfilesystem:DeleteReplicationConfiguration",
                "elasticfilesystem:DeleteTags",
                "elasticfilesystem:DescribeAccessPoints",
                "elasticfilesystem:DescribeAccountPreferences",
                "elasticfilesystem:DescribeBackupPolicy",
                "elasticfilesystem:DescribeFileSystemPolicy",
                "elasticfilesystem:DescribeFileSystems",
                "elasticfilesystem:DescribeLifecycleConfiguration",
                "elasticfilesystem:DescribeMountTargets",
                "elasticfilesystem:DescribeMountTargetSecurityGroups",
                "elasticfilesystem:DescribeReplicationConfigurations",
                "elasticfilesystem:DescribeTags",
                "elasticfilesystem:ModifyMountTargetSecurityGroups",
                "kms:CreateGrant",
                "kms:CreateKey",
                "kms:DescribeKey",
                "kms:GetKeyPolicy",
                "kms:GetKeyRotationStatus",
                "kms:ListResourceTags",
                "kms:ScheduleKeyDeletion",
                "logs:CreateLogGroup",
                "logs:DescribeLogGroups",
                "logs:ListTagsLogGroup",
                "logs:PutRetentionPolicy"
            ],
            "Resource": "*"
        },
        {
            "Sid": "VisualEditor1",
            "Effect": "Allow",
            "Action": [
                "ec2:AllocateAddress",
                "ec2:AssignPrivateIpAddresses",
                "ec2:Associate*",
                "ec2:AttachInternetGateway",
                "ec2:AttachNetworkInterface",
                "ec2:AuthorizeSecurityGroupEgress",
                "ec2:AuthorizeSecurityGroupIngress",     
                "ec2:CreateLaunchTemplate",
                "ec2:CreateLaunchTemplateVersion",
                "ec2:CreateNetworkInterface",
                "ec2:CreateSecurityGroup",
                "ec2:CreateTags",
                "ec2:CreateVolume",
                "ec2:DeleteTags",
                "ec2:Describe*",
                "ec2:DescribeAccountAttributes",
                "ec2:DescribeLaunchTemplates",
                "ec2:DescribeLaunchTemplateVersions",
                "ec2:DescribeNetworkInterfaces",
                "ec2:DescribeSecurityGroups",
                "ec2:DetachNetworkInterface",
                "ec2:DetachVolume",
                "ec2:Disassociate*",
                "ec2:GetLaunchTemplateData",
                "ec2:ModifyLaunchTemplate",
                "ec2:ModifySubnetAttribute",
                "ec2:ModifyVpcEndpoint",
                "ec2:ReleaseAddress",
                "ec2:RevokeSecurityGroupEgress",
                "ec2:RevokeSecurityGroupIngress",
                "ec2:RunInstances",
                "ec2:UpdateSecurityGroupRuleDescriptionsEgress",
                "ec2:UpdateSecurityGroupRuleDescriptionsIngress"
            ],
            "Resource": "*"
        },
        {
            "Sid": "VisualEditor2",
            "Effect": "Allow",
            "Action": [
                "iam:AttachRolePolicy",
                "iam:CreatePolicy",
                "iam:CreateRole",
                "iam:DetachRolePolicy",
                "iam:GetInstanceProfile",
                "iam:GetOpenIDConnectProvider",
                "iam:CreateOpenIDConnectProvider",
                "iam:GetPolicy",
                "iam:GetPolicyVersion",
                "iam:GetRole",
                "iam:GetRolePolicy",
                "iam:List*",
                "iam:ListAttachedRolePolicies",
                "iam:ListRolePolicies",
                "iam:PassRole",
                "iam:TagOpenIDConnectProvider",
                "iam:TagRole",
                "iam:UntagOpenIDConnectProvider",
                "iam:UntagRole"
            ],
            "Resource": "*"
        },
        {
            "Sid": "VisualEditor3",
            "Effect": "Allow",
            "Action": [
                "eks:CreateCluster",
                "eks:CreateFargateProfile",
                "eks:CreateNodegroup",
                "eks:DescribeCluster",
                "eks:DescribeNodegroup",
                "eks:DescribeUpdate",
                "eks:ListClusters",
                "eks:ListNodegroups",
                "eks:ListTagsForResource",
                "eks:TagResource",
                "eks:UntagResource",
                "eks:UpdateClusterConfig",
                "eks:UpdateClusterVersion",
                "eks:UpdateNodegroupConfig",
                "eks:UpdateNodegroupVersion"
            ],
            "Resource": "*"
        },
        {
            "Sid": "VisualEditor4",
            "Effect": "Allow",
            "Action": "s3:*",
            "Resource": [
                "arn:aws:s3:::c3-dev-dts-edge-terraform-state/*",
                "arn:aws:s3:::c3-dev-dts-edge-terraform-state"
            ]
        }
    ]
}
